timetable_cli/__init__.py
timetable_cli/__main__.py
timetable_cli/activity.py
timetable_cli/app.py
timetable_cli/category.py
timetable_cli/cli.py
timetable_cli/colorscheme.py
timetable_cli/enums.py
timetable_cli/prototypes.py
timetable_cli/quote.py
timetable_cli/render.py
timetable_cli/selectors.py
timetable_cli/timetable.py
timetable_cli/utils.py
timetable_cli-0.17.0.dist-info/entry_points.txt
timetable_cli-0.17.0.dist-info/WHEEL
timetable_cli-0.17.0.dist-info/METADATA
timetable_cli-0.17.0.dist-info/RECORD
