Metadata-Version: 2.1
Name: timetable-cli
Version: 0.17.0
Summary: 
Author: 0djentd
Requires-Python: >=3.10,<4.0
Classifier: Programming Language :: Python :: 3
Classifier: Programming Language :: Python :: 3.10
Requires-Dist: appdirs (>=1.4.4,<2.0.0)
Requires-Dist: click (>=8.1.3,<9.0.0)
Requires-Dist: interactive-select (>=0.4.0,<0.5.0)
Requires-Dist: rich (>=12.6.0,<13.0.0)
